Workbook

Sheet Suivi
A1: ID | B1: Épique | C1: Rôle | D1: Je veux… | E1: Afin de… | F1: Critères d'acceptation | G1: Statut | H1: MoSCoW | I1: Points | J1: Dépend de | K1: Sprint | L1: Assigné à | M1: Avancement | N1: Commentaire
A2: US-01 | B2: 1 · Accès et socle | C2: Praticien | D2: entrer dans l'application en saisissant mon nom | E2: accéder aux dossiers | F2: Un nom vide n'ouvre pas la session ; le nom saisi devient l'auteur des tracés et la signature des validations ; il survit à un rechargement | G2: Fait | H2: — | I2: 2 | J2: — | M2: 1
A3: US-02 | B3: 1 · Accès et socle | C3: Praticien | D3: quitter ma session | E3: libérer le poste | F3: L'identité est effacée ; l'écran de connexion revient | G3: Fait | H3: — | I3: 1 | J3: — | M3: 1
A4: US-03 | B4: 1 · Accès et socle | C4: Praticien | D4: choisir un thème clair ou sombre | E4: lire confortablement selon la lumière de la pièce | F4: Le choix est disponible dès la connexion ; il est conservé entre deux sessions ; aucun flash de thème clair au chargement | G4: Fait | H4: — | I4: 3 | J4: — | M4: 1
A5: US-04a | B5: 1 · Accès et socle | C5: Pathologiste qui valide un compte rendu | D5: me connecter avec mon compte Supabase | E5: que ma signature ne puisse pas être prise par quelqu'un qui taperait mon nom | F5: Supabase Auth. Identifiants valides : accès, nom affiché issu du compte ; mot de passe faux : refus avec message neutre ; pas d'inscription libre, comptes créés par un administrateur | G5: À faire | H5: Must | I5: 3 | J5: US-71 | M5: 0
A6: US-04b | B6: 1 · Accès et socle | C6: Établissement qui héberge des données de santé | D6: que l'API refuse toute requête sans jeton Supabase valide | E6: qu'on ne puisse pas contourner l'interface | F6: Sans jeton : 401, aucune donnée ; jeton d'un autre projet Supabase : 401 ; session expirée : retour à la connexion, saisie conservée ; l'adresse de santé reste publique | G6: À faire | H6: Must | I6: 3 | J6: US-04a | M6: 0
A7: US-04c | B7: 1 · Accès et socle | C7: Administrateur qui met en service l'authentification | D7: rattacher les signatures déjà enregistrées à un compte ou les marquer non vérifiées | E7: que l'historique ne mente pas | F7: Nom rattaché à un compte : la validation affiche ce compte ; nom sans compte : mention « Signature non vérifiée » | G7: À faire | H7: Should | I7: 3 | J7: US-04a | M7: 0
A8: US-05 | B8: 1 · Accès et socle | C8: Technicien de laboratoire qui renseigne un prélèvement | D8: ne voir que les étapes de mon rôle | E8: ne pas valider un diagnostic dont je ne réponds pas | F8: Technicien : Prélèvement et Préparation accessibles, Diagnostic absent ; validation Diagnostic envoyée à l'API : refus 403 ; un administrateur change un rôle, effectif à la connexion suivante | G8: À faire | H8: Should | I8: 5 | J8: US-04b | M8: 0
A9: US-06a | B9: 1 · Accès et socle | C9: Établissement soumis à la traçabilité | D9: que chaque action sur un dossier soit journalisée | E9: pouvoir reconstituer qui a fait quoi | F9: Création, validation, modification, suppression : une entrée avec auteur, action, dossier et horodatage ; modifier ou supprimer une entrée par l'API est refusé | G9: À faire | H9: Should | I9: 5 | J9: US-04b | M9: 0
A10: US-06b | B10: 1 · Accès et socle | C10: Administrateur qui instruit une réclamation | D10: lire le journal d'un dossier | E10: savoir qui a fait quoi et quand | F10: Entrées affichées de la plus récente à la plus ancienne ; un pathologiste qui ouvre le journal est refusé | G10: À faire | H10: Should | I10: 3 | J10: US-06a | M10: 0
A11: US-07 | B11: 2 · Dossiers patients | C11: Praticien | D11: créer un dossier patient | E11: y rattacher ses examens | F11: Nom, âge, date de naissance et antécédents sont saisissables ; un identifiant de dossier unique est généré ; le dossier apparaît immédiatement dans la liste | G11: Fait | H11: — | I11: 3 | J11: — | M11: 1
A12: US-08 | B12: 2 · Dossiers patients | C12: Praticien | D12: consulter la liste des dossiers | E12: retrouver celui sur lequel travailler | F12: La liste montre nom, identifiant et composition du dossier ; un liseré indique ce que le dossier contient | G12: Fait | H12: — | I12: 3 | J12: — | M12: 1
A13: US-09 | B13: 2 · Dossiers patients | C13: Responsable de service | D13: lire des indicateurs de suivi | E13: mesurer l'activité | F13: Dossiers suivis, analyses terminées, cas critiques et taux de cas sains sont affichés ; des graphiques accompagnent les chiffres | G13: Fait | H13: — | I13: 5 | J13: — | M13: 1
... A101: US-88 | B101: 4 · Radiologie DICOM | C101: Radiologue qui lit un examen de contrôle | D101: que l'examen précédent du même patient s'ouvre automatiquement à côté | E101: comparer sans le chercher | F101: Inspirée de Sectra et OHIF. L'examen antérieur s'ouvre dans le cadre voisin, dates affichées ; sans antérieur : examen seul, pas de cadre vide | G101: À faire | H101: Could | I101: 5 | J101: US-39, US-87 | M101: 0

Sheet Tableau de bord
A1: Chiron — avancement des user stories
A2: Les chiffres se recalculent à partir de l'onglet Suivi. Ne rien saisir ici.
A4: Total des stories | B4: =COUNTA(Suivi!$A$2:$A$101)
A5: Avancement moyen | B5: =AVERAGE(Suivi!$M$2:$M$101)
A7: Par statut | B7: Nombre | C7: Part
A8: À faire | B8: =COUNTIF(Suivi!$G$2:$G$101,$A8) | C8: =IFERROR(B8/$B$4,0)
A9: En cours | B9: =COUNTIF(Suivi!$G$2:$G$101,$A9) | C9: =IFERROR(B9/$B$4,0)
A10: En revue | B10: =COUNTIF(Suivi!$G$2:$G$101,$A10) | C10: =IFERROR(B10/$B$4,0)
A11: Fait | B11: =COUNTIF(Suivi!$G$2:$G$101,$A11) | C11: =IFERROR(B11/$B$4,0)
A12: Abandonnée | B12: =COUNTIF(Suivi!$G$2:$G$101,$A12) | C12: =IFERROR(B12/$B$4,0)
A15: Par épique | B15: Total | C15: Faites | D15: Reste
A16: 1 · Accès et socle | B16: =COUNTIF(Suivi!$B$2:$B$101,$A16) | C16: =COUNTIFS(Suivi!$B$2:$B$101,$A16,Suivi!$G$2:$G$101,"Fait") | D16: =B16-C16
A17: 2 · Dossiers patients | B17: =COUNTIF(Suivi!$B$2:$B$101,$A17) | C17: =COUNTIFS(Suivi!$B$2:$B$101,$A17,Suivi!$G$2:$G$101,"Fait") | D17: =B17-C17
A18: 3 · Lames de biopsie | B18: =COUNTIF(Suivi!$B$2:$B$101,$A18) | C18: =COUNTIFS(Suivi!$B$2:$B$101,$A18,Suivi!$G$2:$G$101,"Fait") | D18: =B18-C18
A19: 4 · Radiologie DICOM | B19: =COUNTIF(Suivi!$B$2:$B$101,$A19) | C19: =COUNTIFS(Suivi!$B$2:$B$101,$A19,Suivi!$G$2:$G$101,"Fait") | D19: =B19-C19
A20: 5 · Aide au diagnostic | B20: =COUNTIF(Suivi!$B$2:$B$101,$A20) | C20: =COUNTIFS(Suivi!$B$2:$B$101,$A20,Suivi!$G$2:$G$101,"Fait") | D20: =B20-C20
A21: 6 · Compte rendu | B21: =COUNTIF(Suivi!$B$2:$B$101,$A21) | C21: =COUNTIFS(Suivi!$B$2:$B$101,$A21,Suivi!$G$2:$G$101,"Fait") | D21: =B21-C21
A22: 7 · Collaboration | B22: =COUNTIF(Suivi!$B$2:$B$101,$A22) | C22: =COUNTIFS(Suivi!$B$2:$B$101,$A22,Suivi!$G$2:$G$101,"Fait") | D22: =B22-C22
A23: 8 · Robustesse | B23: =COUNTIF(Suivi!$B$2:$B$101,$A23) | C23: =COUNTIFS(Suivi!$B$2:$B$101,$A23,Suivi!$G$2:$G$101,"Fait") | D23: =B23-C23
A24: 9 · Mobilité | B24: =COUNTIF(Suivi!$B$2:$B$101,$A24) | C24: =COUNTIFS(Suivi!$B$2:$B$101,$A24,Suivi!$G$2:$G$101,"Fait") | D24: =B24-C24
A25: 10 · Exploitation | B25: =COUNTIF(Suivi!$B$2:$B$101,$A25) | C25: =COUNTIFS(Suivi!$B$2:$B$101,$A25,Suivi!$G$2:$G$101,"Fait") | D25: =B25-C25
A26: 11 · Orchestration | B26: =COUNTIF(Suivi!$B$2:$B$101,$A26) | C26: =COUNTIFS(Suivi!$B$2:$B$101,$A26,Suivi!$G$2:$G$101,"Fait") | D26: =B26-C26
A28: Reste à faire par MoSCoW | B28: Stories | C28: Points
A29: Must | B29: =COUNTIFS(Suivi!$H$2:$H$101,$A29,Suivi!$G$2:$G$101,"<>Fait") | C29: =SUMIFS(Suivi!$I$2:$I$101,Suivi!$H$2:$H$101,$A29,Suivi!$G$2:$G$101,"<>Fait")
A30: Should | B30: =COUNTIFS(Suivi!$H$2:$H$101,$A30,Suivi!$G$2:$G$101,"<>Fait") | C30: =SUMIFS(Suivi!$I$2:$I$101,Suivi!$H$2:$H$101,$A30,Suivi!$G$2:$G$101,"<>Fait")
A31: Could | B31: =COUNTIFS(Suivi!$H$2:$H$101,$A31,Suivi!$G$2:$G$101,"<>Fait") | C31: =SUMIFS(Suivi!$I$2:$I$101,Suivi!$H$2:$H$101,$A31,Suivi!$G$2:$G$101,"<>Fait")
A32: Won't | B32: =COUNTIFS(Suivi!$H$2:$H$101,$A32,Suivi!$G$2:$G$101,"<>Fait") | C32: =SUMIFS(Suivi!$I$2:$I$101,Suivi!$H$2:$H$101,$A32,Suivi!$G$2:$G$101,"<>Fait")
A35: Points | B35: Total
A36: Points livrés | B36: =SUMIFS(Suivi!$I$2:$I$101,Suivi!$G$2:$G$101,"Fait")
A37: Points restants | B37: =SUMIFS(Suivi!$I$2:$I$101,Suivi!$G$2:$G$101,"<>Fait",Suivi!$G$2:$G$101,"<>Abandonnée")
A38: Part livrée | B38: =IFERROR(B36/(B36+B37),0)
A40: Vélocité et capacité | B40: Valeur
A41: Vélocité moyenne (points par sprint)
A42: Sprints nécessaires pour les Must | B42: =IF(B41>0,ROUNDUP(C29/B41,0),"—")
A43: Sprints nécessaires pour Must et Should | B43: =IF(B41>0,ROUNDUP((C29+C30)/B41,0),"—")
A44: Saisir en B41 la moyenne des points livrés sur les trois derniers sprints. Tant qu'elle est vide, les deux lignes au-dessus affichent un tiret.

Sheet Légende
A1: Comment se servir de ce classeur
A3: Cellules jaunes | B3: Les seules à remplir : Statut, Sprint, Assigné à, Avancement, Commentaire, et la vélocité dans le tableau de bord (B41). Tout le reste décrit la story et ne bouge pas.
A4: Exemple de ligne | B4: Statut : En cours · Sprint : S3 · Assigné à : Rayan · Avancement : 50% · Commentaire : migration Alembic écrite, routes à reprendre
A5: Statut | B5: À faire, En cours, En revue, Fait, Abandonnée. Liste imposée : la saisie libre est refusée.
A6: Avancement | B6: Entre 0 % et 100 %. Les stories déjà livrées sont à 100 %.
A7: MoSCoW | B7: Priorité pour la prochaine livraison. Must : sans elle la livraison n'a pas de sens · Should : importante, contournable · Could : si le temps le permet · Won't : hors périmètre. Les stories faites ne portent pas de classe (—).
A8: Points | B8: Estimation relative en suite de Fibonacci (1, 2, 3, 5, 8, 13). Aucune story à faire ne dépasse 8 : au-delà, elle est découpée. Les points des stories faites sont estimés après coup et servent de base à la vélocité.
A9: Tableau de bord | B9: Recalculé automatiquement depuis l'onglet Suivi. Ne rien y saisir.
A11: Ce qu'il faut savoir avant de planifier
A12: Verrou n° 1 | B12: US-04a, la connexion par Supabase Auth, bloque US-04b, US-04c, US-05, US-06a, US-06b et la collaboration (US-55 à US-58, US-59c, US-60).
A13: Verrou n° 2 | B13: US-28a et US-28b, plusieurs lames datées, bloquent US-28c, US-29, US-30 et US-31. US-39 relève du même chantier côté radiologie.
A14: À commencer | B14: D'abord l'infrastructure demandée par l'encadrement (US-69 à US-72, 16 points), puis US-12, US-13, US-14 et US-61 à US-64, qui ne dépendent de rien (15 points).
A15: Décision en attente | B15: Le backend n'écrit que le statut « Non analysé », le tableau de bord en teste trois autres qui n'existent nulle part. Arrêter la liste des statuts métier avant d'écrire US-13.
A16: Découpage | B16: Directives de l'encadrement : US-69 à US-77 (MinIO remplacé, Supabase, DICOMweb, orchestrateur maison). Inspirées de l'état de l'art : US-78 à US-88. US-04, US-06, US-28, US-43, US-59 et US-65 ont été découpées ; les morceaux gardent l'identifiant d'origine suivi d'une lettre (US-28a, US-28b, US-28c). Hors périmètre (Won't) : voir le document.
A17: Source
A18: Document | B18: Reprend le document « User stories — Chiron. » (critères détaillés en Gherkin). Les stories marquées Fait décrivent le code au 29 septembre 2026 ; celles à faire viennent du backlog de refonte et des planches de maquette.
